org/__init__.py
org/grad/__init__.py
org/grad/enav/__init__.py
org/grad/enav/s201.py
s201_xml_bindings-0.0.4.dist-info/METADATA
s201_xml_bindings-0.0.4.dist-info/WHEEL
s201_xml_bindings-0.0.4.dist-info/entry_points.txt
s201_xml_bindings-0.0.4.dist-info/licenses/LICENCE.md
s201_xml_bindings-0.0.4.dist-info/RECORD
