Metadata-Version: 2.4
Name: s201-xml-bindings
Version: 0.0.4
Summary: A python package implementing the XML bindings for the IALA S-201 data product specification
Author-Email: Nikolaos Vastardis <Nikolaos.Vastardis@gla-rad.org>
License-Expression: Apache-2.0
License-File: LICENCE.md
Classifier: Programming Language :: Python :: 3
Classifier: Operating System :: OS Independent
Project-URL: Homepage, https://github.com/gla-rad/S-100-xmlbindings/tree/python
Project-URL: Issues, https://github.com/gla-rad/S-100-xmlbindings/issues
Requires-Python: >=3.9
